lambpack
