Metadata-Version: 1.1
Name: lambpack
Version: 0.1.1
Summary: Create AWS Lambda packages
Home-page: https://github.com/nathforge/lambpack
Author: Nathan Reynolds
Author-email: email@nreynolds.co.uk
License: UNKNOWN
Platform: UNKNOWN
Classifier: Development Status :: 4 - Beta
Classifier: Intended Audience :: Developers
Classifier: Topic :: Software Development
Classifier: License :: OSI Approved :: MIT License
Classifier: Programming Language :: Python :: 2.7
